vor/__init__.py
vor/_version.py
vor/beanstalk.py
vor/elasticsearch.py
vor/graphite.py
vor/kafka.py
vor/redis.py
vor/test/__init__.py
vor/test/test_beanstalk.py
vor/test/test_elasticsearch.py
vor/test/test_graphite.py
vor/test/test_kafka.py
vor-18.0.0rc1.dist-info/DESCRIPTION.rst
vor-18.0.0rc1.dist-info/METADATA
vor-18.0.0rc1.dist-info/RECORD
vor-18.0.0rc1.dist-info/WHEEL
vor-18.0.0rc1.dist-info/metadata.json
vor-18.0.0rc1.dist-info/top_level.txt
