Metadata-Version: 2.0
Name: vor
Version: 18.0.0rc1
Summary: Services for gathering metrics to send to Graphite
Home-page: http://github.com/ralphm/vor
Author: Ralph Meijer
Author-email: ralphm@ik.nu
License: MIT
Platform: any
Classifier: Programming Language :: Python :: 2.7
Requires-Dist: incremental (>=16.9.0)
Requires-Dist: Twisted[tls] (>=16.0.0)
Provides-Extra: beanstalk
Requires-Dist: pybeanstalk; extra == 'beanstalk'
Provides-Extra: dev
Requires-Dist: pyflakes; extra == 'dev'
Requires-Dist: coverage; extra == 'dev'
Requires-Dist: towncrier; extra == 'dev'
Provides-Extra: elasticsearch
Requires-Dist: treq (>=16.12.0); extra == 'elasticsearch'
Provides-Extra: redis
Requires-Dist: txredis; extra == 'redis'
